{
  "data": [
    {
      "CREATE_DATE": "2017-10-25 09:47:35",
      "JOB_ID": 4811,
      "STATUS": "N",
      "RECORD_NUM": 6063382,
      "AREA_NAME": "广州市",
      "WORK_STATUS": "排队中",
      "FILE_PATH": "/opt/tomcat/rno_tomcat/webapps/ops/op/rno/ana_result/2017/10/2g_angle/",
      "END_MEA_DATE": "2015-08-25 23:59:59",
      "DESC_ID": 12,
      "START_MEA_DATE": "2015-08-25 00:00:00"
    },
    {
      "CREATE_DATE": "2017-10-24 17:46:41",
      "JOB_ID": 4810,
      "STATUS": "N",
      "RECORD_NUM": 800857361,
      "AREA_NAME": "广州市",
      "WORK_STATUS": "排队中",
      "FILE_PATH": "/opt/tomcat/rno_tomcat/webapps/ops/op/rno/ana_result/2017/10/2g_angle/",
      "END_MEA_DATE": "2017-10-22 23:59:59",
      "DESC_ID": 11,
      "START_MEA_DATE": "2015-10-16 00:00:00"
    },
    {
      "CREATE_DATE": "2017-10-18 10:15:14",
      "JOB_ID": 4804,
      "STATUS": "N",
      "RECORD_NUM": 818090736,
      "AREA_NAME": "广州市",
      "WORK_STATUS": "正在计算",
      "FILE_PATH": "/opt/tomcat/rno_tomcat/webapps/ops/op/rno/ana_result/2017/10/2g_angle/",
      "END_MEA_DATE": "2017-10-15 23:59:59",
      "DESC_ID": 10,
      "START_MEA_DATE": "2015-10-09 00:00:00"
    },
    {
      "CREATE_DATE": "2017-10-16 18:22:53",
      "JOB_ID": 4803,
      "STATUS": "N",
      "RECORD_NUM": 818090736,
      "AREA_NAME": "广州市",
      "WORK_STATUS": "正在计算",
      "FILE_PATH": "/opt/tomcat/rno_tomcat/webapps/ops/op/rno/ana_result/2017/10/2g_angle/",
      "END_MEA_DATE": "2017-10-15 23:59:59",
      "DESC_ID": 9,
      "START_MEA_DATE": "2015-10-09 00:00:00"
    },
    {
      "CREATE_DATE": "2017-10-16 15:20:30",
      "JOB_ID": 4800,
      "STATUS": "N",
      "RECORD_NUM": 621101067,
      "AREA_NAME": "广州市",
      "WORK_STATUS": "正在计算",
      "FILE_PATH": "/opt/tomcat/rno_tomcat/webapps/ops/op/rno/ana_result/2017/10/2g_angle/",
      "END_MEA_DATE": "2017-10-16 23:59:59",
      "DESC_ID": 8,
      "START_MEA_DATE": "2016-01-01 00:00:00"
    },
    {
      "CREATE_DATE": "2016-10-20 19:42:16",
      "JOB_ID": 4758,
      "STATUS": "N",
      "RECORD_NUM": 817020568,
      "AREA_NAME": "广州市",
      "WORK_STATUS": "排队中",
      "FILE_PATH": "/opt/tomcat/rno_tomcat/webapps/ops/op/rno/ana_result/2016/10/2g_angle/",
      "END_MEA_DATE": "2016-10-17 23:59:59",
      "DESC_ID": 7,
      "START_MEA_DATE": "2015-10-01 00:00:00"
    },
    {
      "CREATE_DATE": "2016-09-18 14:12:13",
      "JOB_ID": 4757,
      "STATUS": "N",
      "RECORD_NUM": 7063835,
      "AREA_NAME": "广州市",
      "WORK_STATUS": "正在计算",
      "FILE_PATH": "/opt/tomcat/rno_tomcat/webapps/ops/op/rno/ana_result/2016/9/2g_angle/",
      "END_MEA_DATE": "2016-09-18 23:59:59",
      "DESC_ID": 6,
      "START_MEA_DATE": "2016-09-01 00:00:00"
    }
  ]
}